.DS_Store
basencode/__init__.py
basencode/tests.py
basencode-2.1.0.dist-info/LICENSE
basencode-2.1.0.dist-info/METADATA
basencode-2.1.0.dist-info/WHEEL
basencode-2.1.0.dist-info/top_level.txt
basencode-2.1.0.dist-info/RECORD
