Metadata-Version: 2.1
Name: basencode
Version: 2.1.0
Summary: Convert numbers of any base back and forth.
Home-page: https://basencode.readthedocs.io/
Author: Pranav Pooruli
Author-email: pranav.pooruli@gmail.com
License: MIT
Classifier: License :: OSI Approved :: MIT License
Classifier: Programming Language :: Python :: 3
Classifier: Programming Language :: Python :: 3.9
License-File: LICENSE
